{"lastModified":1430413377000,"name":"Saidoren","realm":"Sanguino","battlegroup":"Cruelty / Crueldad","class":6,"race":10,"gender":0,"level":100,"achievementPoints":7375,"thumbnail":"zuljin/240/89408752-avatar.jpg","calcClass":"d","items":{"averageItemLevel":688,"averageItemLevelEquipped":683,"head":{"id":113894,"name":"Gran yelmo bañado en lava","icon":"inv_plate_raidwarriormythic_o_01helm","quality":4,"itemLevel":695,"tooltipParams":{"gem0":115812,"transmogItem":46115},"stats":[{"stat":59,"amount":225},{"stat":32,"amount":169},{"stat":74,"amount":306},{"stat":7,"amount":459}],"armor":308,"context":"raid-mythic","bonusLists":[565,567]},"neck":{"id":113858,"name":"Gargantilla de desplazamiento violento","icon":"inv_6_0raid_necklace_2a","quality":4,"itemLevel":685,"tooltipParams":{"enchant":5319},"stats":[{"stat":50,"amount":102},{"stat":72,"amount":157},{"stat":36,"amount":106},{"stat":7,"amount":235}],"armor":0,"context":"raid-mythic","bonusLists":[567]},"shoulder":{"id":113990,"name":"Bufas aceleradas","icon":"inv_shoulder_plate_raidpaladin_o_01","quality":4,"itemLevel":680,"tooltipParams":{"transmogItem":51418},"stats":[{"stat":59,"amount":130},{"stat":49,"amount":135},{"stat":74,"amount":200},{"stat":7,"amount":300}],"armor":272,"context":"raid-heroic","bonusLists":[566]},"back":{"id":113873,"name":"Gran capa de gronn cosida","icon":"inv_cape_draenorraid_d_01plate_dk","quality":4,"itemLevel":701,"tooltipParams":{"enchant":5312,"transmogItem":113937},"stats":[{"stat":50,"amount":125},{"stat":40,"amount":115},{"stat":72,"amount":182},{"stat":7,"amount":273}],"armor":73,"context":"raid-mythic","bonusLists":[562,567]},"chest":{"id":115537,"name":"Coraza de placas óseas de craneogro","icon":"inv_plate_raiddeathknight_o_01chest","quality":4,"itemLevel":686,"tooltipParams":{"set":[115537,115535],"transmogItem":51134},"stats":[{"stat":59,"amount":165},{"stat":49,"amount":201},{"stat":4,"amount":281},{"stat":7,"amount":422}],"armor":369,"context":"raid-heroic","bonusLists":[561,566]},"tabard":{"id":43155,"name":"Tabardo de la Espada de Ébano","icon":"inv_shirt_guildtabard_01","quality":1,"itemLevel":75,"tooltipParams":{},"stats":[],"armor":0,"context":"vendor","bonusLists":[]},"wrist":{"id":113896,"name":"Brazales de derritepieles","icon":"inv_plate_raiddeathknight_o_01bracer","quality":4,"itemLevel":680,"tooltipParams":{},"stats":[{"stat":59,"amount":76},{"stat":49,"amount":114},{"stat":74,"amount":150},{"stat":7,"amount":225}],"armor":159,"context":"raid-heroic","bonusLists":[566]},"hands":{"id":113925,"name":"Guanteletes Furiallama","icon":"inv_plate_raidwarrior_o_01gloves","quality":4,"itemLevel":665,"tooltipParams":{"gem0":115812,"transmogItem":45833},"stats":[{"stat":49,"amount":127},{"stat":74,"amount":174},{"stat":36,"amount":96},{"stat":7,"amount":260}],"armor":217,"context":"raid-normal","bonusLists":[563]},"waist":{"id":113659,"name":"Gran cinturón de masticarnes","icon":"inv_plate_raidwarrior_o_01belt","quality":4,"itemLevel":685,"tooltipParams":{"transmogItem":34651},"stats":[{"stat":32,"amount":154},{"stat":63,"amount":119},{"stat":74,"amount":209},{"stat":36,"amount":116},{"stat":7,"amount":314}],"armor":207,"context":"raid-mythic","bonusLists":[40,567]},"legs":{"id":115535,"name":"Grebas de placas óseas de craneogro","icon":"inv_plate_raiddeathknight_o_01pant","quality":4,"itemLevel":680,"tooltipParams":{"set":[115537,115535],"transmogItem":51131},"stats":[{"stat":59,"amount":177},{"stat":32,"amount":177},{"stat":4,"amount":266},{"stat":7,"amount":399}],"armor":317,"context":"raid-heroic","bonusLists":[566]},"feet":{"id":114235,"name":"Botas de veracero del armonioso","icon":"inv_plate_draenorcrafted_d_01boot","quality":4,"itemLevel":680,"tooltipParams":{"transmogItem":77170},"stats":[{"stat":49,"amount":152},{"stat":40,"amount":101},{"stat":74,"amount":200},{"stat":7,"amount":300}],"armor":249,"context":"trade-skill","bonusLists":[216,534,593]},"finger1":{"id":118303,"name":"Sortija de solium de invisibilidad hechicera vinculada","icon":"inv_misc_6oring_bluelv3","quality":4,"itemLevel":690,"tooltipParams":{"enchant":5326},"stats":[{"stat":50,"amount":116},{"stat":40,"amount":99},{"stat":72,"amount":164},{"stat":7,"amount":246}],"armor":0,"context":"quest-reward","bonusLists":[]},"finger2":{"id":113908,"name":"Anillo de filo tajoafilado","icon":"inv_ringwod_d2_1","quality":4,"itemLevel":680,"tooltipParams":{"enchant":5326},"stats":[{"stat":50,"amount":81},{"stat":49,"amount":111},{"stat":72,"amount":150},{"stat":7,"amount":225}],"armor":0,"context":"raid-heroic","bonusLists":[566]},"trinket1":{"id":113905,"name":"Tablilla de tensor colaborativo","icon":"inv_misc_trinket6oih_orb4","quality":4,"itemLevel":680,"tooltipParams":{},"stats":[{"stat":49,"amount":481}],"armor":0,"context":"raid-heroic","bonusLists":[566]},"trinket2":{"id":113893,"name":"Puerta del Horno de Fundición","icon":"inv_misc_trinket6oih_ironskull1","quality":4,"itemLevel":680,"tooltipParams":{"gem0":115812},"stats":[{"stat":50,"amount":414}],"armor":0,"context":"raid-heroic","bonusLists":[564,566]},"mainHand":{"id":113953,"name":"Vara de control de Thogar","icon":"ivn_polearm_2h_draenorraid_d_01","quality":4,"itemLevel":680,"tooltipParams":{"enchant":3368,"transmogItem":50048},"stats":[{"stat":49,"amount":139},{"stat":4,"amount":266},{"stat":36,"amount":200},{"stat":7,"amount":399}],"armor":0,"weaponInfo":{"damage":{"min":1376,"max":2066,"exactMin":1376.0,"exactMax":2065.0},"weaponSpeed":3.6,"dps":477.9167},"context":"raid-heroic","bonusLists":[566]}},"totalHonorableKills":2612}