{"lastModified":1424328766000,"name":"Syptor","realm":"Zul'jin","battlegroup":"Cruelty / Crueldad","class":1,"race":2,"gender":0,"level":100,"achievementPoints":14220,"thumbnail":"zuljin/246/70766838-avatar.jpg","calcClass":"Z","items":{"averageItemLevel":629,"averageItemLevelEquipped":629,"head":{"id":109986,"name":"Corona de placas verdeantes","icon":"inv_helm_draenordungeon_c_01","quality":3,"itemLevel":615,"tooltipParams":{},"stats":[{"stat":32,"amount":78},{"stat":49,"amount":108},{"stat":74,"amount":145},{"stat":7,"amount":218}],"armor":245,"context":"dungeon-normal","bonusLists":[522]},"neck":{"id":117369,"name":"Gargantilla de corazón puro","icon":"inv_jewelry_necklace_45","quality":4,"itemLevel":635,"tooltipParams":{},"stats":[{"stat":32,"amount":62},{"stat":4,"amount":98},{"stat":36,"amount":68},{"stat":7,"amount":148}],"armor":0,"context":"dungeon-normal","bonusLists":[553]},"shoulder":{"id":116236,"name":"Bufas de bomba de hierro","icon":"inv_plate_draenorlfr_c_01shoulders","quality":4,"itemLevel":640,"tooltipParams":{},"stats":[{"stat":40,"amount":74},{"stat":49,"amount":102},{"stat":74,"amount":138},{"stat":7,"amount":207}],"armor":242,"context":"raid-finder","bonusLists":[563]},"back":{"id":116298,"name":"Mantón marcado por las llamas","icon":"inv_cape_draenorraid_d_01leather_druid","quality":4,"itemLevel":640,"tooltipParams":{},"stats":[{"stat":50,"amount":62},{"stat":32,"amount":73},{"stat":72,"amount":103},{"stat":7,"amount":155}],"armor":47,"context":"raid-finder","bonusLists":[]},"chest":{"id":109893,"name":"Pechera de placas verdeantes","icon":"inv_chest_plate_draenordungeon_c_01","quality":3,"itemLevel":630,"tooltipParams":{},"stats":[{"stat":40,"amount":111},{"stat":32,"amount":111},{"stat":74,"amount":167},{"stat":7,"amount":251}],"armor":314,"context":"dungeon-heroic","bonusLists":[523,524]},"wrist":{"id":109878,"name":"Ataduras de oracero","icon":"inv_bracer_plate_draenordungeon_c_01","quality":3,"itemLevel":600,"tooltipParams":{},"stats":[{"stat":40,"amount":48},{"stat":74,"amount":71},{"stat":36,"amount":46},{"stat":7,"amount":107}],"armor":126,"context":"dungeon-level-up-4","bonusLists":[521]},"hands":{"id":116233,"name":"Mandiletes de infusión ardiente","icon":"inv_plate_draenorlfr_c_01glove","quality":4,"itemLevel":640,"tooltipParams":{},"stats":[{"stat":49,"amount":105},{"stat":32,"amount":70},{"stat":74,"amount":138},{"stat":7,"amount":207}],"armor":202,"context":"raid-finder","bonusLists":[]},"waist":{"id":114704,"name":"Faja de trueno de las llanuras","icon":"inv_belt_plate_draenorquest95_b_01","quality":3,"itemLevel":605,"tooltipParams":{"tinker":4222},"stats":[{"stat":49,"amount":52},{"stat":32,"amount":75},{"stat":74,"amount":99},{"stat":7,"amount":149}],"armor":165,"context":"quest-reward","bonusLists":[171]},"legs":{"id":109820,"name":"Quijotes de oracero","icon":"inv_pant_plate_draenordungeon_c_01","quality":3,"itemLevel":630,"tooltipParams":{},"stats":[{"stat":59,"amount":85},{"stat":32,"amount":127},{"stat":74,"amount":167},{"stat":7,"amount":251}],"armor":275,"context":"dungeon-heroic","bonusLists":[524]},"feet":{"id":109793,"name":"Grebas encarnadas","icon":"inv_boot_plate_draenordungeon_c_01","quality":3,"itemLevel":630,"tooltipParams":{},"stats":[{"stat":32,"amount":90},{"stat":74,"amount":126},{"stat":36,"amount":74},{"stat":7,"amount":189}],"armor":216,"context":"dungeon-heroic","bonusLists":[524]},"finger1":{"id":115794,"name":"Anillo de taladita resplandeciente del armonioso","icon":"inv_60crafted_ring2d","quality":4,"itemLevel":640,"tooltipParams":{},"stats":[{"stat":49,"amount":71},{"stat":40,"amount":65},{"stat":4,"amount":103},{"stat":7,"amount":155}],"armor":0,"context":"trade-skill","bonusLists":[208,525,540]},"finger2":{"id":109771,"name":"Anillo de mitosis ensangrentado","icon":"inv_60dungeon_ring3a","quality":3,"itemLevel":630,"tooltipParams":{},"stats":[{"stat":49,"amount":49},{"stat":63,"amount":54},{"stat":4,"amount":94},{"stat":36,"amount":71},{"stat":7,"amount":141}],"armor":0,"context":"dungeon-heroic","bonusLists":[40,524]},"trinket1":{"id":110010,"name":"Mota de corrupción","icon":"inv_misc_shadowegg","quality":3,"itemLevel":630,"tooltipParams":{},"stats":[{"stat":4,"amount":159},{"stat":49,"amount":159}],"armor":0,"context":"dungeon-heroic","bonusLists":[524]},"trinket2":{"id":110017,"name":"Granada aturdidora de déspota","icon":"inv_misc_bomb_02","quality":3,"itemLevel":630,"tooltipParams":{},"stats":[{"stat":50,"amount":106}],"armor":0,"context":"dungeon-heroic","bonusLists":[524]},"mainHand":{"id":116361,"name":"Destral de carnicero cruel","icon":"inv_axe_1h_draenorhonor_c_01","quality":4,"itemLevel":640,"tooltipParams":{},"stats":[{"stat":32,"amount":55},{"stat":4,"amount":79},{"stat":36,"amount":49},{"stat":7,"amount":118}],"armor":0,"weaponInfo":{"damage":{"min":466,"max":866,"exactMin":466.0,"exactMax":866.0},"weaponSpeed":2.6,"dps":256.15387},"context":"raid-finder","bonusLists":[]},"offHand":{"id":110053,"name":"Gran escudo rompeflechas","icon":"inv_shield_draenordungeon_c_02","quality":3,"itemLevel":630,"tooltipParams":{},"stats":[{"stat":32,"amount":52},{"stat":40,"amount":69},{"stat":4,"amount":94},{"stat":7,"amount":141}],"armor":739,"context":"dungeon-heroic","bonusLists":[524]}},"totalHonorableKills":65}